ytsummary/__init__.py
ytsummary/core.py
ytsummary/summarizer.py
ytsummary/youtube_utils.py
ytsummary-0.1.1.dist-info/licenses/LICENSE
ytsummary-0.1.1.dist-info/METADATA
ytsummary-0.1.1.dist-info/WHEEL
ytsummary-0.1.1.dist-info/top_level.txt
ytsummary-0.1.1.dist-info/RECORD
