Metadata-Version: 2.4
Name: ytsummary
Version: 0.1.1
Summary: YouTube video summary generator
Author-email: Sangwon Chae <your.email@example.com>
License: MIT
Project-URL: Homepage, https://github.com/yourusername/ytsummary
Project-URL: Bug Tracker, https://github.com/yourusername/ytsummary/issues
Requires-Python: >=3.8
License-File: LICENSE
Requires-Dist: requests>=2.25.0
Requires-Dist: beautifulsoup4>=4.9.3
Requires-Dist: youtube_transcript_api>=0.4.4
Requires-Dist: transformers>=4.30.0
Requires-Dist: torch>=2.0.0
Requires-Dist: pytube>=12.1.0
Dynamic: license-file
